{
  "Top": "my_prj",
  "RtlTop": "my_prj",
  "RtlPrefix": "",
  "SourceLanguage": "cpp",
  "ResetStyle": "control",
  "GenerateBdFiles": "0",
  "HostMachineBits": "64",
  "Target": {
    "Family": "virtexuplus",
    "Device": "xcvu9p",
    "Package": "-flgc2104",
    "Speed": "-1-e"
  },
  "HlsSolution": {
    
  },
  "Args": {
    "x": {
      "index": "0",
      "type": {
        "kinds": ["array"],
        "dataType": "ap_fixed",
        "arraySizes": ["7"]
      }
    },
    "score": {
      "index": "1",
      "type": {
        "kinds": ["array"],
        "dataType": "ap_fixed",
        "arraySizes": ["2"]
      }
    },
    "tree_scores": {
      "index": "2",
      "type": {
        "kinds": ["array"],
        "dataType": "ap_fixed",
        "arraySizes": ["100"]
      }
    }
  },
  "Return": {
    
  },
  "ClockInfo": {
    "ClockName": "ap_clk",
    "ClockPeriod": "4.17",
    "IsCombLogic": "0",
    "II": "1",
    "Latency": "6",
    "Uncertainty": "0.52125"
  },
  "Xdc": {"OocClocks": ["create_clock -name ap_clk -period 4.170 [get_ports ap_clk]"]},
  "Ipx": {
    "Vendor": "xilinx.com",
    "Library": "hls",
    "Name": "my_prj",
    "Version": "1.0",
    "DisplayName": "My_prj",
    "Revision": "",
    "Description": "An IP generated by Vivado HLS",
    "Taxonomy": "\/VIVADO_HLS_IP",
    "AutoFamilySupport": ""
  },
  "Files": {
    "CSource": ["..\/..\/firmware\/my_prj.cpp"],
    "Vhdl": [
      "impl\/vhdl\/decision_function.vhd",
      "impl\/vhdl\/decision_function_1.vhd",
      "impl\/vhdl\/my_prj_mux_73_11_1_1.vhd",
      "impl\/vhdl\/my_prj_mux_83_11_1_1.vhd",
      "impl\/vhdl\/my_prj_mux_154_1_1_1.vhd",
      "impl\/vhdl\/my_prj_mux_154_32_1_1.vhd",
      "impl\/vhdl\/my_prj.vhd"
    ],
    "Verilog": [
      "impl\/verilog\/decision_function.v",
      "impl\/verilog\/decision_function_1.v",
      "impl\/verilog\/my_prj_mux_73_11_1_1.v",
      "impl\/verilog\/my_prj_mux_83_11_1_1.v",
      "impl\/verilog\/my_prj_mux_154_1_1_1.v",
      "impl\/verilog\/my_prj_mux_154_32_1_1.v",
      "impl\/verilog\/my_prj.v"
    ],
    "Misc": ["impl\/misc\/logo.png"],
    "DesignXml": "\/nfs\/data41\/csavard\/CS_conifer\/conifer\/11_6_opt\/my_prj_prj\/solution1\/.autopilot\/db\/my_prj.design.xml",
    "DebugDir": "\/nfs\/data41\/csavard\/CS_conifer\/conifer\/11_6_opt\/my_prj_prj\/solution1\/.debug",
    "ProtoInst": ["\/nfs\/data41\/csavard\/CS_conifer\/conifer\/11_6_opt\/my_prj_prj\/solution1\/.debug\/my_prj.protoinst"]
  },
  "SubcoreInfo": {
    "HasXpmMemory": false,
    "HasClockedDsp": false,
    "IP": []
  },
  "Interfaces": {
    "ap_clk": {
      "type": "clock",
      "ctype": {"CLK": {"Type": "bool"}},
      "bundle_name": "ap_clk",
      "bundle_role": "default",
      "reset": "ap_rst"
    },
    "ap_ctrl": {
      "type": "ap_ctrl",
      "ctrl_ports": "ap_start ap_done ap_idle ap_ready",
      "ctype": {
        "start": {"Type": "bool"},
        "done": {"Type": "bool"},
        "idle": {"Type": "bool"},
        "ready": {"Type": "bool"}
      }
    },
    "ap_rst": {
      "type": "reset",
      "polarity": "ACTIVE_HIGH",
      "ctype": {"RST": {"Type": "bool"}},
      "bundle_name": "ap_rst",
      "bundle_role": "default"
    },
    "score_0_V": {
      "type": "data",
      "dir": "out",
      "width": "11",
      "ctype": {"DATA": {
          "Type": "real fixed signed 5",
          "Width": "11"
        }},
      "bundle_name": "score_0_V",
      "bundle_role": "default"
    },
    "score_1_V": {
      "type": "data",
      "dir": "in",
      "width": "11",
      "ctype": {"DATA": {
          "Type": "real fixed signed 5",
          "Width": "11"
        }},
      "bundle_name": "score_1_V",
      "bundle_role": "default"
    },
    "tree_scores_0_V": {
      "type": "data",
      "dir": "out",
      "width": "11",
      "ctype": {"DATA": {
          "Type": "real fixed signed 5",
          "Width": "11"
        }},
      "bundle_name": "tree_scores_0_V",
      "bundle_role": "default"
    },
    "tree_scores_1_V": {
      "type": "data",
      "dir": "out",
      "width": "11",
      "ctype": {"DATA": {
          "Type": "real fixed signed 5",
          "Width": "11"
        }},
      "bundle_name": "tree_scores_1_V",
      "bundle_role": "default"
    },
    "tree_scores_2_V": {
      "type": "data",
      "dir": "out",
      "width": "11",
      "ctype": {"DATA": {
          "Type": "real fixed signed 5",
          "Width": "11"
        }},
      "bundle_name": "tree_scores_2_V",
      "bundle_role": "default"
    },
    "tree_scores_3_V": {
      "type": "data",
      "dir": "out",
      "width": "11",
      "ctype": {"DATA": {
          "Type": "real fixed signed 5",
          "Width": "11"
        }},
      "bundle_name": "tree_scores_3_V",
      "bundle_role": "default"
    },
    "tree_scores_4_V": {
      "type": "data",
      "dir": "out",
      "width": "11",
      "ctype": {"DATA": {
          "Type": "real fixed signed 5",
          "Width": "11"
        }},
      "bundle_name": "tree_scores_4_V",
      "bundle_role": "default"
    },
    "tree_scores_5_V": {
      "type": "data",
      "dir": "out",
      "width": "11",
      "ctype": {"DATA": {
          "Type": "real fixed signed 5",
          "Width": "11"
        }},
      "bundle_name": "tree_scores_5_V",
      "bundle_role": "default"
    },
    "tree_scores_6_V": {
      "type": "data",
      "dir": "out",
      "width": "11",
      "ctype": {"DATA": {
          "Type": "real fixed signed 5",
          "Width": "11"
        }},
      "bundle_name": "tree_scores_6_V",
      "bundle_role": "default"
    },
    "tree_scores_7_V": {
      "type": "data",
      "dir": "out",
      "width": "11",
      "ctype": {"DATA": {
          "Type": "real fixed signed 5",
          "Width": "11"
        }},
      "bundle_name": "tree_scores_7_V",
      "bundle_role": "default"
    },
    "tree_scores_8_V": {
      "type": "data",
      "dir": "out",
      "width": "11",
      "ctype": {"DATA": {
          "Type": "real fixed signed 5",
          "Width": "11"
        }},
      "bundle_name": "tree_scores_8_V",
      "bundle_role": "default"
    },
    "tree_scores_9_V": {
      "type": "data",
      "dir": "out",
      "width": "11",
      "ctype": {"DATA": {
          "Type": "real fixed signed 5",
          "Width": "11"
        }},
      "bundle_name": "tree_scores_9_V",
      "bundle_role": "default"
    },
    "tree_scores_10_V": {
      "type": "data",
      "dir": "out",
      "width": "11",
      "ctype": {"DATA": {
          "Type": "real fixed signed 5",
          "Width": "11"
        }},
      "bundle_name": "tree_scores_10_V",
      "bundle_role": "default"
    },
    "tree_scores_11_V": {
      "type": "data",
      "dir": "out",
      "width": "11",
      "ctype": {"DATA": {
          "Type": "real fixed signed 5",
          "Width": "11"
        }},
      "bundle_name": "tree_scores_11_V",
      "bundle_role": "default"
    },
    "tree_scores_12_V": {
      "type": "data",
      "dir": "out",
      "width": "11",
      "ctype": {"DATA": {
          "Type": "real fixed signed 5",
          "Width": "11"
        }},
      "bundle_name": "tree_scores_12_V",
      "bundle_role": "default"
    },
    "tree_scores_13_V": {
      "type": "data",
      "dir": "out",
      "width": "11",
      "ctype": {"DATA": {
          "Type": "real fixed signed 5",
          "Width": "11"
        }},
      "bundle_name": "tree_scores_13_V",
      "bundle_role": "default"
    },
    "tree_scores_14_V": {
      "type": "data",
      "dir": "out",
      "width": "11",
      "ctype": {"DATA": {
          "Type": "real fixed signed 5",
          "Width": "11"
        }},
      "bundle_name": "tree_scores_14_V",
      "bundle_role": "default"
    },
    "tree_scores_15_V": {
      "type": "data",
      "dir": "out",
      "width": "11",
      "ctype": {"DATA": {
          "Type": "real fixed signed 5",
          "Width": "11"
        }},
      "bundle_name": "tree_scores_15_V",
      "bundle_role": "default"
    },
    "tree_scores_16_V": {
      "type": "data",
      "dir": "out",
      "width": "11",
      "ctype": {"DATA": {
          "Type": "real fixed signed 5",
          "Width": "11"
        }},
      "bundle_name": "tree_scores_16_V",
      "bundle_role": "default"
    },
    "tree_scores_17_V": {
      "type": "data",
      "dir": "out",
      "width": "11",
      "ctype": {"DATA": {
          "Type": "real fixed signed 5",
          "Width": "11"
        }},
      "bundle_name": "tree_scores_17_V",
      "bundle_role": "default"
    },
    "tree_scores_18_V": {
      "type": "data",
      "dir": "out",
      "width": "11",
      "ctype": {"DATA": {
          "Type": "real fixed signed 5",
          "Width": "11"
        }},
      "bundle_name": "tree_scores_18_V",
      "bundle_role": "default"
    },
    "tree_scores_19_V": {
      "type": "data",
      "dir": "out",
      "width": "11",
      "ctype": {"DATA": {
          "Type": "real fixed signed 5",
          "Width": "11"
        }},
      "bundle_name": "tree_scores_19_V",
      "bundle_role": "default"
    },
    "tree_scores_20_V": {
      "type": "data",
      "dir": "out",
      "width": "11",
      "ctype": {"DATA": {
          "Type": "real fixed signed 5",
          "Width": "11"
        }},
      "bundle_name": "tree_scores_20_V",
      "bundle_role": "default"
    },
    "tree_scores_21_V": {
      "type": "data",
      "dir": "out",
      "width": "11",
      "ctype": {"DATA": {
          "Type": "real fixed signed 5",
          "Width": "11"
        }},
      "bundle_name": "tree_scores_21_V",
      "bundle_role": "default"
    },
    "tree_scores_22_V": {
      "type": "data",
      "dir": "out",
      "width": "11",
      "ctype": {"DATA": {
          "Type": "real fixed signed 5",
          "Width": "11"
        }},
      "bundle_name": "tree_scores_22_V",
      "bundle_role": "default"
    },
    "tree_scores_23_V": {
      "type": "data",
      "dir": "out",
      "width": "11",
      "ctype": {"DATA": {
          "Type": "real fixed signed 5",
          "Width": "11"
        }},
      "bundle_name": "tree_scores_23_V",
      "bundle_role": "default"
    },
    "tree_scores_24_V": {
      "type": "data",
      "dir": "out",
      "width": "11",
      "ctype": {"DATA": {
          "Type": "real fixed signed 5",
          "Width": "11"
        }},
      "bundle_name": "tree_scores_24_V",
      "bundle_role": "default"
    },
    "tree_scores_25_V": {
      "type": "data",
      "dir": "out",
      "width": "11",
      "ctype": {"DATA": {
          "Type": "real fixed signed 5",
          "Width": "11"
        }},
      "bundle_name": "tree_scores_25_V",
      "bundle_role": "default"
    },
    "tree_scores_26_V": {
      "type": "data",
      "dir": "out",
      "width": "11",
      "ctype": {"DATA": {
          "Type": "real fixed signed 5",
          "Width": "11"
        }},
      "bundle_name": "tree_scores_26_V",
      "bundle_role": "default"
    },
    "tree_scores_27_V": {
      "type": "data",
      "dir": "out",
      "width": "11",
      "ctype": {"DATA": {
          "Type": "real fixed signed 5",
          "Width": "11"
        }},
      "bundle_name": "tree_scores_27_V",
      "bundle_role": "default"
    },
    "tree_scores_28_V": {
      "type": "data",
      "dir": "out",
      "width": "11",
      "ctype": {"DATA": {
          "Type": "real fixed signed 5",
          "Width": "11"
        }},
      "bundle_name": "tree_scores_28_V",
      "bundle_role": "default"
    },
    "tree_scores_29_V": {
      "type": "data",
      "dir": "out",
      "width": "11",
      "ctype": {"DATA": {
          "Type": "real fixed signed 5",
          "Width": "11"
        }},
      "bundle_name": "tree_scores_29_V",
      "bundle_role": "default"
    },
    "tree_scores_30_V": {
      "type": "data",
      "dir": "out",
      "width": "11",
      "ctype": {"DATA": {
          "Type": "real fixed signed 5",
          "Width": "11"
        }},
      "bundle_name": "tree_scores_30_V",
      "bundle_role": "default"
    },
    "tree_scores_31_V": {
      "type": "data",
      "dir": "out",
      "width": "11",
      "ctype": {"DATA": {
          "Type": "real fixed signed 5",
          "Width": "11"
        }},
      "bundle_name": "tree_scores_31_V",
      "bundle_role": "default"
    },
    "tree_scores_32_V": {
      "type": "data",
      "dir": "out",
      "width": "11",
      "ctype": {"DATA": {
          "Type": "real fixed signed 5",
          "Width": "11"
        }},
      "bundle_name": "tree_scores_32_V",
      "bundle_role": "default"
    },
    "tree_scores_33_V": {
      "type": "data",
      "dir": "out",
      "width": "11",
      "ctype": {"DATA": {
          "Type": "real fixed signed 5",
          "Width": "11"
        }},
      "bundle_name": "tree_scores_33_V",
      "bundle_role": "default"
    },
    "tree_scores_34_V": {
      "type": "data",
      "dir": "out",
      "width": "11",
      "ctype": {"DATA": {
          "Type": "real fixed signed 5",
          "Width": "11"
        }},
      "bundle_name": "tree_scores_34_V",
      "bundle_role": "default"
    },
    "tree_scores_35_V": {
      "type": "data",
      "dir": "out",
      "width": "11",
      "ctype": {"DATA": {
          "Type": "real fixed signed 5",
          "Width": "11"
        }},
      "bundle_name": "tree_scores_35_V",
      "bundle_role": "default"
    },
    "tree_scores_36_V": {
      "type": "data",
      "dir": "out",
      "width": "11",
      "ctype": {"DATA": {
          "Type": "real fixed signed 5",
          "Width": "11"
        }},
      "bundle_name": "tree_scores_36_V",
      "bundle_role": "default"
    },
    "tree_scores_37_V": {
      "type": "data",
      "dir": "out",
      "width": "11",
      "ctype": {"DATA": {
          "Type": "real fixed signed 5",
          "Width": "11"
        }},
      "bundle_name": "tree_scores_37_V",
      "bundle_role": "default"
    },
    "tree_scores_38_V": {
      "type": "data",
      "dir": "out",
      "width": "11",
      "ctype": {"DATA": {
          "Type": "real fixed signed 5",
          "Width": "11"
        }},
      "bundle_name": "tree_scores_38_V",
      "bundle_role": "default"
    },
    "tree_scores_39_V": {
      "type": "data",
      "dir": "out",
      "width": "11",
      "ctype": {"DATA": {
          "Type": "real fixed signed 5",
          "Width": "11"
        }},
      "bundle_name": "tree_scores_39_V",
      "bundle_role": "default"
    },
    "tree_scores_40_V": {
      "type": "data",
      "dir": "out",
      "width": "11",
      "ctype": {"DATA": {
          "Type": "real fixed signed 5",
          "Width": "11"
        }},
      "bundle_name": "tree_scores_40_V",
      "bundle_role": "default"
    },
    "tree_scores_41_V": {
      "type": "data",
      "dir": "out",
      "width": "11",
      "ctype": {"DATA": {
          "Type": "real fixed signed 5",
          "Width": "11"
        }},
      "bundle_name": "tree_scores_41_V",
      "bundle_role": "default"
    },
    "tree_scores_42_V": {
      "type": "data",
      "dir": "out",
      "width": "11",
      "ctype": {"DATA": {
          "Type": "real fixed signed 5",
          "Width": "11"
        }},
      "bundle_name": "tree_scores_42_V",
      "bundle_role": "default"
    },
    "tree_scores_43_V": {
      "type": "data",
      "dir": "out",
      "width": "11",
      "ctype": {"DATA": {
          "Type": "real fixed signed 5",
          "Width": "11"
        }},
      "bundle_name": "tree_scores_43_V",
      "bundle_role": "default"
    },
    "tree_scores_44_V": {
      "type": "data",
      "dir": "out",
      "width": "11",
      "ctype": {"DATA": {
          "Type": "real fixed signed 5",
          "Width": "11"
        }},
      "bundle_name": "tree_scores_44_V",
      "bundle_role": "default"
    },
    "tree_scores_45_V": {
      "type": "data",
      "dir": "out",
      "width": "11",
      "ctype": {"DATA": {
          "Type": "real fixed signed 5",
          "Width": "11"
        }},
      "bundle_name": "tree_scores_45_V",
      "bundle_role": "default"
    },
    "tree_scores_46_V": {
      "type": "data",
      "dir": "out",
      "width": "11",
      "ctype": {"DATA": {
          "Type": "real fixed signed 5",
          "Width": "11"
        }},
      "bundle_name": "tree_scores_46_V",
      "bundle_role": "default"
    },
    "tree_scores_47_V": {
      "type": "data",
      "dir": "out",
      "width": "11",
      "ctype": {"DATA": {
          "Type": "real fixed signed 5",
          "Width": "11"
        }},
      "bundle_name": "tree_scores_47_V",
      "bundle_role": "default"
    },
    "tree_scores_48_V": {
      "type": "data",
      "dir": "out",
      "width": "11",
      "ctype": {"DATA": {
          "Type": "real fixed signed 5",
          "Width": "11"
        }},
      "bundle_name": "tree_scores_48_V",
      "bundle_role": "default"
    },
    "tree_scores_49_V": {
      "type": "data",
      "dir": "out",
      "width": "11",
      "ctype": {"DATA": {
          "Type": "real fixed signed 5",
          "Width": "11"
        }},
      "bundle_name": "tree_scores_49_V",
      "bundle_role": "default"
    },
    "tree_scores_50_V": {
      "type": "data",
      "dir": "out",
      "width": "11",
      "ctype": {"DATA": {
          "Type": "real fixed signed 5",
          "Width": "11"
        }},
      "bundle_name": "tree_scores_50_V",
      "bundle_role": "default"
    },
    "tree_scores_51_V": {
      "type": "data",
      "dir": "out",
      "width": "11",
      "ctype": {"DATA": {
          "Type": "real fixed signed 5",
          "Width": "11"
        }},
      "bundle_name": "tree_scores_51_V",
      "bundle_role": "default"
    },
    "tree_scores_52_V": {
      "type": "data",
      "dir": "out",
      "width": "11",
      "ctype": {"DATA": {
          "Type": "real fixed signed 5",
          "Width": "11"
        }},
      "bundle_name": "tree_scores_52_V",
      "bundle_role": "default"
    },
    "tree_scores_53_V": {
      "type": "data",
      "dir": "out",
      "width": "11",
      "ctype": {"DATA": {
          "Type": "real fixed signed 5",
          "Width": "11"
        }},
      "bundle_name": "tree_scores_53_V",
      "bundle_role": "default"
    },
    "tree_scores_54_V": {
      "type": "data",
      "dir": "out",
      "width": "11",
      "ctype": {"DATA": {
          "Type": "real fixed signed 5",
          "Width": "11"
        }},
      "bundle_name": "tree_scores_54_V",
      "bundle_role": "default"
    },
    "tree_scores_55_V": {
      "type": "data",
      "dir": "out",
      "width": "11",
      "ctype": {"DATA": {
          "Type": "real fixed signed 5",
          "Width": "11"
        }},
      "bundle_name": "tree_scores_55_V",
      "bundle_role": "default"
    },
    "tree_scores_56_V": {
      "type": "data",
      "dir": "out",
      "width": "11",
      "ctype": {"DATA": {
          "Type": "real fixed signed 5",
          "Width": "11"
        }},
      "bundle_name": "tree_scores_56_V",
      "bundle_role": "default"
    },
    "tree_scores_57_V": {
      "type": "data",
      "dir": "out",
      "width": "11",
      "ctype": {"DATA": {
          "Type": "real fixed signed 5",
          "Width": "11"
        }},
      "bundle_name": "tree_scores_57_V",
      "bundle_role": "default"
    },
    "tree_scores_58_V": {
      "type": "data",
      "dir": "out",
      "width": "11",
      "ctype": {"DATA": {
          "Type": "real fixed signed 5",
          "Width": "11"
        }},
      "bundle_name": "tree_scores_58_V",
      "bundle_role": "default"
    },
    "tree_scores_59_V": {
      "type": "data",
      "dir": "out",
      "width": "11",
      "ctype": {"DATA": {
          "Type": "real fixed signed 5",
          "Width": "11"
        }},
      "bundle_name": "tree_scores_59_V",
      "bundle_role": "default"
    },
    "tree_scores_60_V": {
      "type": "data",
      "dir": "out",
      "width": "11",
      "ctype": {"DATA": {
          "Type": "real fixed signed 5",
          "Width": "11"
        }},
      "bundle_name": "tree_scores_60_V",
      "bundle_role": "default"
    },
    "tree_scores_61_V": {
      "type": "data",
      "dir": "out",
      "width": "11",
      "ctype": {"DATA": {
          "Type": "real fixed signed 5",
          "Width": "11"
        }},
      "bundle_name": "tree_scores_61_V",
      "bundle_role": "default"
    },
    "tree_scores_62_V": {
      "type": "data",
      "dir": "out",
      "width": "11",
      "ctype": {"DATA": {
          "Type": "real fixed signed 5",
          "Width": "11"
        }},
      "bundle_name": "tree_scores_62_V",
      "bundle_role": "default"
    },
    "tree_scores_63_V": {
      "type": "data",
      "dir": "out",
      "width": "11",
      "ctype": {"DATA": {
          "Type": "real fixed signed 5",
          "Width": "11"
        }},
      "bundle_name": "tree_scores_63_V",
      "bundle_role": "default"
    },
    "tree_scores_64_V": {
      "type": "data",
      "dir": "out",
      "width": "11",
      "ctype": {"DATA": {
          "Type": "real fixed signed 5",
          "Width": "11"
        }},
      "bundle_name": "tree_scores_64_V",
      "bundle_role": "default"
    },
    "tree_scores_65_V": {
      "type": "data",
      "dir": "out",
      "width": "11",
      "ctype": {"DATA": {
          "Type": "real fixed signed 5",
          "Width": "11"
        }},
      "bundle_name": "tree_scores_65_V",
      "bundle_role": "default"
    },
    "tree_scores_66_V": {
      "type": "data",
      "dir": "out",
      "width": "11",
      "ctype": {"DATA": {
          "Type": "real fixed signed 5",
          "Width": "11"
        }},
      "bundle_name": "tree_scores_66_V",
      "bundle_role": "default"
    },
    "tree_scores_67_V": {
      "type": "data",
      "dir": "out",
      "width": "11",
      "ctype": {"DATA": {
          "Type": "real fixed signed 5",
          "Width": "11"
        }},
      "bundle_name": "tree_scores_67_V",
      "bundle_role": "default"
    },
    "tree_scores_68_V": {
      "type": "data",
      "dir": "out",
      "width": "11",
      "ctype": {"DATA": {
          "Type": "real fixed signed 5",
          "Width": "11"
        }},
      "bundle_name": "tree_scores_68_V",
      "bundle_role": "default"
    },
    "tree_scores_69_V": {
      "type": "data",
      "dir": "out",
      "width": "11",
      "ctype": {"DATA": {
          "Type": "real fixed signed 5",
          "Width": "11"
        }},
      "bundle_name": "tree_scores_69_V",
      "bundle_role": "default"
    },
    "tree_scores_70_V": {
      "type": "data",
      "dir": "out",
      "width": "11",
      "ctype": {"DATA": {
          "Type": "real fixed signed 5",
          "Width": "11"
        }},
      "bundle_name": "tree_scores_70_V",
      "bundle_role": "default"
    },
    "tree_scores_71_V": {
      "type": "data",
      "dir": "out",
      "width": "11",
      "ctype": {"DATA": {
          "Type": "real fixed signed 5",
          "Width": "11"
        }},
      "bundle_name": "tree_scores_71_V",
      "bundle_role": "default"
    },
    "tree_scores_72_V": {
      "type": "data",
      "dir": "out",
      "width": "11",
      "ctype": {"DATA": {
          "Type": "real fixed signed 5",
          "Width": "11"
        }},
      "bundle_name": "tree_scores_72_V",
      "bundle_role": "default"
    },
    "tree_scores_73_V": {
      "type": "data",
      "dir": "out",
      "width": "11",
      "ctype": {"DATA": {
          "Type": "real fixed signed 5",
          "Width": "11"
        }},
      "bundle_name": "tree_scores_73_V",
      "bundle_role": "default"
    },
    "tree_scores_74_V": {
      "type": "data",
      "dir": "out",
      "width": "11",
      "ctype": {"DATA": {
          "Type": "real fixed signed 5",
          "Width": "11"
        }},
      "bundle_name": "tree_scores_74_V",
      "bundle_role": "default"
    },
    "tree_scores_75_V": {
      "type": "data",
      "dir": "out",
      "width": "11",
      "ctype": {"DATA": {
          "Type": "real fixed signed 5",
          "Width": "11"
        }},
      "bundle_name": "tree_scores_75_V",
      "bundle_role": "default"
    },
    "tree_scores_76_V": {
      "type": "data",
      "dir": "out",
      "width": "11",
      "ctype": {"DATA": {
          "Type": "real fixed signed 5",
          "Width": "11"
        }},
      "bundle_name": "tree_scores_76_V",
      "bundle_role": "default"
    },
    "tree_scores_77_V": {
      "type": "data",
      "dir": "out",
      "width": "11",
      "ctype": {"DATA": {
          "Type": "real fixed signed 5",
          "Width": "11"
        }},
      "bundle_name": "tree_scores_77_V",
      "bundle_role": "default"
    },
    "tree_scores_78_V": {
      "type": "data",
      "dir": "out",
      "width": "11",
      "ctype": {"DATA": {
          "Type": "real fixed signed 5",
          "Width": "11"
        }},
      "bundle_name": "tree_scores_78_V",
      "bundle_role": "default"
    },
    "tree_scores_79_V": {
      "type": "data",
      "dir": "out",
      "width": "11",
      "ctype": {"DATA": {
          "Type": "real fixed signed 5",
          "Width": "11"
        }},
      "bundle_name": "tree_scores_79_V",
      "bundle_role": "default"
    },
    "tree_scores_80_V": {
      "type": "data",
      "dir": "out",
      "width": "11",
      "ctype": {"DATA": {
          "Type": "real fixed signed 5",
          "Width": "11"
        }},
      "bundle_name": "tree_scores_80_V",
      "bundle_role": "default"
    },
    "tree_scores_81_V": {
      "type": "data",
      "dir": "out",
      "width": "11",
      "ctype": {"DATA": {
          "Type": "real fixed signed 5",
          "Width": "11"
        }},
      "bundle_name": "tree_scores_81_V",
      "bundle_role": "default"
    },
    "tree_scores_82_V": {
      "type": "data",
      "dir": "out",
      "width": "11",
      "ctype": {"DATA": {
          "Type": "real fixed signed 5",
          "Width": "11"
        }},
      "bundle_name": "tree_scores_82_V",
      "bundle_role": "default"
    },
    "tree_scores_83_V": {
      "type": "data",
      "dir": "out",
      "width": "11",
      "ctype": {"DATA": {
          "Type": "real fixed signed 5",
          "Width": "11"
        }},
      "bundle_name": "tree_scores_83_V",
      "bundle_role": "default"
    },
    "tree_scores_84_V": {
      "type": "data",
      "dir": "out",
      "width": "11",
      "ctype": {"DATA": {
          "Type": "real fixed signed 5",
          "Width": "11"
        }},
      "bundle_name": "tree_scores_84_V",
      "bundle_role": "default"
    },
    "tree_scores_85_V": {
      "type": "data",
      "dir": "out",
      "width": "11",
      "ctype": {"DATA": {
          "Type": "real fixed signed 5",
          "Width": "11"
        }},
      "bundle_name": "tree_scores_85_V",
      "bundle_role": "default"
    },
    "tree_scores_86_V": {
      "type": "data",
      "dir": "out",
      "width": "11",
      "ctype": {"DATA": {
          "Type": "real fixed signed 5",
          "Width": "11"
        }},
      "bundle_name": "tree_scores_86_V",
      "bundle_role": "default"
    },
    "tree_scores_87_V": {
      "type": "data",
      "dir": "out",
      "width": "11",
      "ctype": {"DATA": {
          "Type": "real fixed signed 5",
          "Width": "11"
        }},
      "bundle_name": "tree_scores_87_V",
      "bundle_role": "default"
    },
    "tree_scores_88_V": {
      "type": "data",
      "dir": "out",
      "width": "11",
      "ctype": {"DATA": {
          "Type": "real fixed signed 5",
          "Width": "11"
        }},
      "bundle_name": "tree_scores_88_V",
      "bundle_role": "default"
    },
    "tree_scores_89_V": {
      "type": "data",
      "dir": "out",
      "width": "11",
      "ctype": {"DATA": {
          "Type": "real fixed signed 5",
          "Width": "11"
        }},
      "bundle_name": "tree_scores_89_V",
      "bundle_role": "default"
    },
    "tree_scores_90_V": {
      "type": "data",
      "dir": "out",
      "width": "11",
      "ctype": {"DATA": {
          "Type": "real fixed signed 5",
          "Width": "11"
        }},
      "bundle_name": "tree_scores_90_V",
      "bundle_role": "default"
    },
    "tree_scores_91_V": {
      "type": "data",
      "dir": "out",
      "width": "11",
      "ctype": {"DATA": {
          "Type": "real fixed signed 5",
          "Width": "11"
        }},
      "bundle_name": "tree_scores_91_V",
      "bundle_role": "default"
    },
    "tree_scores_92_V": {
      "type": "data",
      "dir": "out",
      "width": "11",
      "ctype": {"DATA": {
          "Type": "real fixed signed 5",
          "Width": "11"
        }},
      "bundle_name": "tree_scores_92_V",
      "bundle_role": "default"
    },
    "tree_scores_93_V": {
      "type": "data",
      "dir": "out",
      "width": "11",
      "ctype": {"DATA": {
          "Type": "real fixed signed 5",
          "Width": "11"
        }},
      "bundle_name": "tree_scores_93_V",
      "bundle_role": "default"
    },
    "tree_scores_94_V": {
      "type": "data",
      "dir": "out",
      "width": "11",
      "ctype": {"DATA": {
          "Type": "real fixed signed 5",
          "Width": "11"
        }},
      "bundle_name": "tree_scores_94_V",
      "bundle_role": "default"
    },
    "tree_scores_95_V": {
      "type": "data",
      "dir": "out",
      "width": "11",
      "ctype": {"DATA": {
          "Type": "real fixed signed 5",
          "Width": "11"
        }},
      "bundle_name": "tree_scores_95_V",
      "bundle_role": "default"
    },
    "tree_scores_96_V": {
      "type": "data",
      "dir": "out",
      "width": "11",
      "ctype": {"DATA": {
          "Type": "real fixed signed 5",
          "Width": "11"
        }},
      "bundle_name": "tree_scores_96_V",
      "bundle_role": "default"
    },
    "tree_scores_97_V": {
      "type": "data",
      "dir": "out",
      "width": "11",
      "ctype": {"DATA": {
          "Type": "real fixed signed 5",
          "Width": "11"
        }},
      "bundle_name": "tree_scores_97_V",
      "bundle_role": "default"
    },
    "tree_scores_98_V": {
      "type": "data",
      "dir": "out",
      "width": "11",
      "ctype": {"DATA": {
          "Type": "real fixed signed 5",
          "Width": "11"
        }},
      "bundle_name": "tree_scores_98_V",
      "bundle_role": "default"
    },
    "tree_scores_99_V": {
      "type": "data",
      "dir": "out",
      "width": "11",
      "ctype": {"DATA": {
          "Type": "real fixed signed 5",
          "Width": "11"
        }},
      "bundle_name": "tree_scores_99_V",
      "bundle_role": "default"
    },
    "x_0_V": {
      "type": "data",
      "dir": "in",
      "width": "11",
      "ctype": {"DATA": {
          "Type": "real fixed signed 5",
          "Width": "11"
        }},
      "bundle_name": "x_0_V",
      "bundle_role": "default"
    },
    "x_1_V": {
      "type": "data",
      "dir": "in",
      "width": "11",
      "ctype": {"DATA": {
          "Type": "real fixed signed 5",
          "Width": "11"
        }},
      "bundle_name": "x_1_V",
      "bundle_role": "default"
    },
    "x_2_V": {
      "type": "data",
      "dir": "in",
      "width": "11",
      "ctype": {"DATA": {
          "Type": "real fixed signed 5",
          "Width": "11"
        }},
      "bundle_name": "x_2_V",
      "bundle_role": "default"
    },
    "x_3_V": {
      "type": "data",
      "dir": "in",
      "width": "11",
      "ctype": {"DATA": {
          "Type": "real fixed signed 5",
          "Width": "11"
        }},
      "bundle_name": "x_3_V",
      "bundle_role": "default"
    },
    "x_4_V": {
      "type": "data",
      "dir": "in",
      "width": "11",
      "ctype": {"DATA": {
          "Type": "real fixed signed 5",
          "Width": "11"
        }},
      "bundle_name": "x_4_V",
      "bundle_role": "default"
    },
    "x_5_V": {
      "type": "data",
      "dir": "in",
      "width": "11",
      "ctype": {"DATA": {
          "Type": "real fixed signed 5",
          "Width": "11"
        }},
      "bundle_name": "x_5_V",
      "bundle_role": "default"
    },
    "x_6_V": {
      "type": "data",
      "dir": "in",
      "width": "11",
      "ctype": {"DATA": {
          "Type": "real fixed signed 5",
          "Width": "11"
        }},
      "bundle_name": "x_6_V",
      "bundle_role": "default"
    }
  },
  "RtlPorts": {
    "ap_clk": {
      "dir": "in",
      "width": "1"
    },
    "ap_rst": {
      "dir": "in",
      "width": "1"
    },
    "ap_start": {
      "dir": "in",
      "width": "1"
    },
    "ap_done": {
      "dir": "out",
      "width": "1"
    },
    "ap_idle": {
      "dir": "out",
      "width": "1"
    },
    "ap_ready": {
      "dir": "out",
      "width": "1"
    },
    "x_0_V": {
      "dir": "in",
      "width": "11"
    },
    "x_1_V": {
      "dir": "in",
      "width": "11"
    },
    "x_2_V": {
      "dir": "in",
      "width": "11"
    },
    "x_3_V": {
      "dir": "in",
      "width": "11"
    },
    "x_4_V": {
      "dir": "in",
      "width": "11"
    },
    "x_5_V": {
      "dir": "in",
      "width": "11"
    },
    "x_6_V": {
      "dir": "in",
      "width": "11"
    },
    "score_0_V": {
      "dir": "out",
      "width": "11"
    },
    "score_0_V_ap_vld": {
      "dir": "out",
      "width": "1"
    },
    "score_1_V": {
      "dir": "in",
      "width": "11"
    },
    "tree_scores_0_V": {
      "dir": "out",
      "width": "11"
    },
    "tree_scores_0_V_ap_vld": {
      "dir": "out",
      "width": "1"
    },
    "tree_scores_1_V": {
      "dir": "out",
      "width": "11"
    },
    "tree_scores_1_V_ap_vld": {
      "dir": "out",
      "width": "1"
    },
    "tree_scores_2_V": {
      "dir": "out",
      "width": "11"
    },
    "tree_scores_2_V_ap_vld": {
      "dir": "out",
      "width": "1"
    },
    "tree_scores_3_V": {
      "dir": "out",
      "width": "11"
    },
    "tree_scores_3_V_ap_vld": {
      "dir": "out",
      "width": "1"
    },
    "tree_scores_4_V": {
      "dir": "out",
      "width": "11"
    },
    "tree_scores_4_V_ap_vld": {
      "dir": "out",
      "width": "1"
    },
    "tree_scores_5_V": {
      "dir": "out",
      "width": "11"
    },
    "tree_scores_5_V_ap_vld": {
      "dir": "out",
      "width": "1"
    },
    "tree_scores_6_V": {
      "dir": "out",
      "width": "11"
    },
    "tree_scores_6_V_ap_vld": {
      "dir": "out",
      "width": "1"
    },
    "tree_scores_7_V": {
      "dir": "out",
      "width": "11"
    },
    "tree_scores_7_V_ap_vld": {
      "dir": "out",
      "width": "1"
    },
    "tree_scores_8_V": {
      "dir": "out",
      "width": "11"
    },
    "tree_scores_8_V_ap_vld": {
      "dir": "out",
      "width": "1"
    },
    "tree_scores_9_V": {
      "dir": "out",
      "width": "11"
    },
    "tree_scores_9_V_ap_vld": {
      "dir": "out",
      "width": "1"
    },
    "tree_scores_10_V": {
      "dir": "out",
      "width": "11"
    },
    "tree_scores_10_V_ap_vld": {
      "dir": "out",
      "width": "1"
    },
    "tree_scores_11_V": {
      "dir": "out",
      "width": "11"
    },
    "tree_scores_11_V_ap_vld": {
      "dir": "out",
      "width": "1"
    },
    "tree_scores_12_V": {
      "dir": "out",
      "width": "11"
    },
    "tree_scores_12_V_ap_vld": {
      "dir": "out",
      "width": "1"
    },
    "tree_scores_13_V": {
      "dir": "out",
      "width": "11"
    },
    "tree_scores_13_V_ap_vld": {
      "dir": "out",
      "width": "1"
    },
    "tree_scores_14_V": {
      "dir": "out",
      "width": "11"
    },
    "tree_scores_14_V_ap_vld": {
      "dir": "out",
      "width": "1"
    },
    "tree_scores_15_V": {
      "dir": "out",
      "width": "11"
    },
    "tree_scores_15_V_ap_vld": {
      "dir": "out",
      "width": "1"
    },
    "tree_scores_16_V": {
      "dir": "out",
      "width": "11"
    },
    "tree_scores_16_V_ap_vld": {
      "dir": "out",
      "width": "1"
    },
    "tree_scores_17_V": {
      "dir": "out",
      "width": "11"
    },
    "tree_scores_17_V_ap_vld": {
      "dir": "out",
      "width": "1"
    },
    "tree_scores_18_V": {
      "dir": "out",
      "width": "11"
    },
    "tree_scores_18_V_ap_vld": {
      "dir": "out",
      "width": "1"
    },
    "tree_scores_19_V": {
      "dir": "out",
      "width": "11"
    },
    "tree_scores_19_V_ap_vld": {
      "dir": "out",
      "width": "1"
    },
    "tree_scores_20_V": {
      "dir": "out",
      "width": "11"
    },
    "tree_scores_20_V_ap_vld": {
      "dir": "out",
      "width": "1"
    },
    "tree_scores_21_V": {
      "dir": "out",
      "width": "11"
    },
    "tree_scores_21_V_ap_vld": {
      "dir": "out",
      "width": "1"
    },
    "tree_scores_22_V": {
      "dir": "out",
      "width": "11"
    },
    "tree_scores_22_V_ap_vld": {
      "dir": "out",
      "width": "1"
    },
    "tree_scores_23_V": {
      "dir": "out",
      "width": "11"
    },
    "tree_scores_23_V_ap_vld": {
      "dir": "out",
      "width": "1"
    },
    "tree_scores_24_V": {
      "dir": "out",
      "width": "11"
    },
    "tree_scores_24_V_ap_vld": {
      "dir": "out",
      "width": "1"
    },
    "tree_scores_25_V": {
      "dir": "out",
      "width": "11"
    },
    "tree_scores_25_V_ap_vld": {
      "dir": "out",
      "width": "1"
    },
    "tree_scores_26_V": {
      "dir": "out",
      "width": "11"
    },
    "tree_scores_26_V_ap_vld": {
      "dir": "out",
      "width": "1"
    },
    "tree_scores_27_V": {
      "dir": "out",
      "width": "11"
    },
    "tree_scores_27_V_ap_vld": {
      "dir": "out",
      "width": "1"
    },
    "tree_scores_28_V": {
      "dir": "out",
      "width": "11"
    },
    "tree_scores_28_V_ap_vld": {
      "dir": "out",
      "width": "1"
    },
    "tree_scores_29_V": {
      "dir": "out",
      "width": "11"
    },
    "tree_scores_29_V_ap_vld": {
      "dir": "out",
      "width": "1"
    },
    "tree_scores_30_V": {
      "dir": "out",
      "width": "11"
    },
    "tree_scores_30_V_ap_vld": {
      "dir": "out",
      "width": "1"
    },
    "tree_scores_31_V": {
      "dir": "out",
      "width": "11"
    },
    "tree_scores_31_V_ap_vld": {
      "dir": "out",
      "width": "1"
    },
    "tree_scores_32_V": {
      "dir": "out",
      "width": "11"
    },
    "tree_scores_32_V_ap_vld": {
      "dir": "out",
      "width": "1"
    },
    "tree_scores_33_V": {
      "dir": "out",
      "width": "11"
    },
    "tree_scores_33_V_ap_vld": {
      "dir": "out",
      "width": "1"
    },
    "tree_scores_34_V": {
      "dir": "out",
      "width": "11"
    },
    "tree_scores_34_V_ap_vld": {
      "dir": "out",
      "width": "1"
    },
    "tree_scores_35_V": {
      "dir": "out",
      "width": "11"
    },
    "tree_scores_35_V_ap_vld": {
      "dir": "out",
      "width": "1"
    },
    "tree_scores_36_V": {
      "dir": "out",
      "width": "11"
    },
    "tree_scores_36_V_ap_vld": {
      "dir": "out",
      "width": "1"
    },
    "tree_scores_37_V": {
      "dir": "out",
      "width": "11"
    },
    "tree_scores_37_V_ap_vld": {
      "dir": "out",
      "width": "1"
    },
    "tree_scores_38_V": {
      "dir": "out",
      "width": "11"
    },
    "tree_scores_38_V_ap_vld": {
      "dir": "out",
      "width": "1"
    },
    "tree_scores_39_V": {
      "dir": "out",
      "width": "11"
    },
    "tree_scores_39_V_ap_vld": {
      "dir": "out",
      "width": "1"
    },
    "tree_scores_40_V": {
      "dir": "out",
      "width": "11"
    },
    "tree_scores_40_V_ap_vld": {
      "dir": "out",
      "width": "1"
    },
    "tree_scores_41_V": {
      "dir": "out",
      "width": "11"
    },
    "tree_scores_41_V_ap_vld": {
      "dir": "out",
      "width": "1"
    },
    "tree_scores_42_V": {
      "dir": "out",
      "width": "11"
    },
    "tree_scores_42_V_ap_vld": {
      "dir": "out",
      "width": "1"
    },
    "tree_scores_43_V": {
      "dir": "out",
      "width": "11"
    },
    "tree_scores_43_V_ap_vld": {
      "dir": "out",
      "width": "1"
    },
    "tree_scores_44_V": {
      "dir": "out",
      "width": "11"
    },
    "tree_scores_44_V_ap_vld": {
      "dir": "out",
      "width": "1"
    },
    "tree_scores_45_V": {
      "dir": "out",
      "width": "11"
    },
    "tree_scores_45_V_ap_vld": {
      "dir": "out",
      "width": "1"
    },
    "tree_scores_46_V": {
      "dir": "out",
      "width": "11"
    },
    "tree_scores_46_V_ap_vld": {
      "dir": "out",
      "width": "1"
    },
    "tree_scores_47_V": {
      "dir": "out",
      "width": "11"
    },
    "tree_scores_47_V_ap_vld": {
      "dir": "out",
      "width": "1"
    },
    "tree_scores_48_V": {
      "dir": "out",
      "width": "11"
    },
    "tree_scores_48_V_ap_vld": {
      "dir": "out",
      "width": "1"
    },
    "tree_scores_49_V": {
      "dir": "out",
      "width": "11"
    },
    "tree_scores_49_V_ap_vld": {
      "dir": "out",
      "width": "1"
    },
    "tree_scores_50_V": {
      "dir": "out",
      "width": "11"
    },
    "tree_scores_50_V_ap_vld": {
      "dir": "out",
      "width": "1"
    },
    "tree_scores_51_V": {
      "dir": "out",
      "width": "11"
    },
    "tree_scores_51_V_ap_vld": {
      "dir": "out",
      "width": "1"
    },
    "tree_scores_52_V": {
      "dir": "out",
      "width": "11"
    },
    "tree_scores_52_V_ap_vld": {
      "dir": "out",
      "width": "1"
    },
    "tree_scores_53_V": {
      "dir": "out",
      "width": "11"
    },
    "tree_scores_53_V_ap_vld": {
      "dir": "out",
      "width": "1"
    },
    "tree_scores_54_V": {
      "dir": "out",
      "width": "11"
    },
    "tree_scores_54_V_ap_vld": {
      "dir": "out",
      "width": "1"
    },
    "tree_scores_55_V": {
      "dir": "out",
      "width": "11"
    },
    "tree_scores_55_V_ap_vld": {
      "dir": "out",
      "width": "1"
    },
    "tree_scores_56_V": {
      "dir": "out",
      "width": "11"
    },
    "tree_scores_56_V_ap_vld": {
      "dir": "out",
      "width": "1"
    },
    "tree_scores_57_V": {
      "dir": "out",
      "width": "11"
    },
    "tree_scores_57_V_ap_vld": {
      "dir": "out",
      "width": "1"
    },
    "tree_scores_58_V": {
      "dir": "out",
      "width": "11"
    },
    "tree_scores_58_V_ap_vld": {
      "dir": "out",
      "width": "1"
    },
    "tree_scores_59_V": {
      "dir": "out",
      "width": "11"
    },
    "tree_scores_59_V_ap_vld": {
      "dir": "out",
      "width": "1"
    },
    "tree_scores_60_V": {
      "dir": "out",
      "width": "11"
    },
    "tree_scores_60_V_ap_vld": {
      "dir": "out",
      "width": "1"
    },
    "tree_scores_61_V": {
      "dir": "out",
      "width": "11"
    },
    "tree_scores_61_V_ap_vld": {
      "dir": "out",
      "width": "1"
    },
    "tree_scores_62_V": {
      "dir": "out",
      "width": "11"
    },
    "tree_scores_62_V_ap_vld": {
      "dir": "out",
      "width": "1"
    },
    "tree_scores_63_V": {
      "dir": "out",
      "width": "11"
    },
    "tree_scores_63_V_ap_vld": {
      "dir": "out",
      "width": "1"
    },
    "tree_scores_64_V": {
      "dir": "out",
      "width": "11"
    },
    "tree_scores_64_V_ap_vld": {
      "dir": "out",
      "width": "1"
    },
    "tree_scores_65_V": {
      "dir": "out",
      "width": "11"
    },
    "tree_scores_65_V_ap_vld": {
      "dir": "out",
      "width": "1"
    },
    "tree_scores_66_V": {
      "dir": "out",
      "width": "11"
    },
    "tree_scores_66_V_ap_vld": {
      "dir": "out",
      "width": "1"
    },
    "tree_scores_67_V": {
      "dir": "out",
      "width": "11"
    },
    "tree_scores_67_V_ap_vld": {
      "dir": "out",
      "width": "1"
    },
    "tree_scores_68_V": {
      "dir": "out",
      "width": "11"
    },
    "tree_scores_68_V_ap_vld": {
      "dir": "out",
      "width": "1"
    },
    "tree_scores_69_V": {
      "dir": "out",
      "width": "11"
    },
    "tree_scores_69_V_ap_vld": {
      "dir": "out",
      "width": "1"
    },
    "tree_scores_70_V": {
      "dir": "out",
      "width": "11"
    },
    "tree_scores_70_V_ap_vld": {
      "dir": "out",
      "width": "1"
    },
    "tree_scores_71_V": {
      "dir": "out",
      "width": "11"
    },
    "tree_scores_71_V_ap_vld": {
      "dir": "out",
      "width": "1"
    },
    "tree_scores_72_V": {
      "dir": "out",
      "width": "11"
    },
    "tree_scores_72_V_ap_vld": {
      "dir": "out",
      "width": "1"
    },
    "tree_scores_73_V": {
      "dir": "out",
      "width": "11"
    },
    "tree_scores_73_V_ap_vld": {
      "dir": "out",
      "width": "1"
    },
    "tree_scores_74_V": {
      "dir": "out",
      "width": "11"
    },
    "tree_scores_74_V_ap_vld": {
      "dir": "out",
      "width": "1"
    },
    "tree_scores_75_V": {
      "dir": "out",
      "width": "11"
    },
    "tree_scores_75_V_ap_vld": {
      "dir": "out",
      "width": "1"
    },
    "tree_scores_76_V": {
      "dir": "out",
      "width": "11"
    },
    "tree_scores_76_V_ap_vld": {
      "dir": "out",
      "width": "1"
    },
    "tree_scores_77_V": {
      "dir": "out",
      "width": "11"
    },
    "tree_scores_77_V_ap_vld": {
      "dir": "out",
      "width": "1"
    },
    "tree_scores_78_V": {
      "dir": "out",
      "width": "11"
    },
    "tree_scores_78_V_ap_vld": {
      "dir": "out",
      "width": "1"
    },
    "tree_scores_79_V": {
      "dir": "out",
      "width": "11"
    },
    "tree_scores_79_V_ap_vld": {
      "dir": "out",
      "width": "1"
    },
    "tree_scores_80_V": {
      "dir": "out",
      "width": "11"
    },
    "tree_scores_80_V_ap_vld": {
      "dir": "out",
      "width": "1"
    },
    "tree_scores_81_V": {
      "dir": "out",
      "width": "11"
    },
    "tree_scores_81_V_ap_vld": {
      "dir": "out",
      "width": "1"
    },
    "tree_scores_82_V": {
      "dir": "out",
      "width": "11"
    },
    "tree_scores_82_V_ap_vld": {
      "dir": "out",
      "width": "1"
    },
    "tree_scores_83_V": {
      "dir": "out",
      "width": "11"
    },
    "tree_scores_83_V_ap_vld": {
      "dir": "out",
      "width": "1"
    },
    "tree_scores_84_V": {
      "dir": "out",
      "width": "11"
    },
    "tree_scores_84_V_ap_vld": {
      "dir": "out",
      "width": "1"
    },
    "tree_scores_85_V": {
      "dir": "out",
      "width": "11"
    },
    "tree_scores_85_V_ap_vld": {
      "dir": "out",
      "width": "1"
    },
    "tree_scores_86_V": {
      "dir": "out",
      "width": "11"
    },
    "tree_scores_86_V_ap_vld": {
      "dir": "out",
      "width": "1"
    },
    "tree_scores_87_V": {
      "dir": "out",
      "width": "11"
    },
    "tree_scores_87_V_ap_vld": {
      "dir": "out",
      "width": "1"
    },
    "tree_scores_88_V": {
      "dir": "out",
      "width": "11"
    },
    "tree_scores_88_V_ap_vld": {
      "dir": "out",
      "width": "1"
    },
    "tree_scores_89_V": {
      "dir": "out",
      "width": "11"
    },
    "tree_scores_89_V_ap_vld": {
      "dir": "out",
      "width": "1"
    },
    "tree_scores_90_V": {
      "dir": "out",
      "width": "11"
    },
    "tree_scores_90_V_ap_vld": {
      "dir": "out",
      "width": "1"
    },
    "tree_scores_91_V": {
      "dir": "out",
      "width": "11"
    },
    "tree_scores_91_V_ap_vld": {
      "dir": "out",
      "width": "1"
    },
    "tree_scores_92_V": {
      "dir": "out",
      "width": "11"
    },
    "tree_scores_92_V_ap_vld": {
      "dir": "out",
      "width": "1"
    },
    "tree_scores_93_V": {
      "dir": "out",
      "width": "11"
    },
    "tree_scores_93_V_ap_vld": {
      "dir": "out",
      "width": "1"
    },
    "tree_scores_94_V": {
      "dir": "out",
      "width": "11"
    },
    "tree_scores_94_V_ap_vld": {
      "dir": "out",
      "width": "1"
    },
    "tree_scores_95_V": {
      "dir": "out",
      "width": "11"
    },
    "tree_scores_95_V_ap_vld": {
      "dir": "out",
      "width": "1"
    },
    "tree_scores_96_V": {
      "dir": "out",
      "width": "11"
    },
    "tree_scores_96_V_ap_vld": {
      "dir": "out",
      "width": "1"
    },
    "tree_scores_97_V": {
      "dir": "out",
      "width": "11"
    },
    "tree_scores_97_V_ap_vld": {
      "dir": "out",
      "width": "1"
    },
    "tree_scores_98_V": {
      "dir": "out",
      "width": "11"
    },
    "tree_scores_98_V_ap_vld": {
      "dir": "out",
      "width": "1"
    },
    "tree_scores_99_V": {
      "dir": "out",
      "width": "11"
    },
    "tree_scores_99_V_ap_vld": {
      "dir": "out",
      "width": "1"
    }
  },
  "ModuleInfo": {
    "Hierarchy": {
      "ModuleName": "my_prj",
      "Instances": [{
          "ModuleName": "decision_function_1",
          "InstanceName": "grp_decision_function_1_fu_989",
          "Instances": [
            {
              "ModuleName": "decision_function",
              "InstanceName": "grp_decision_function_fu_478"
            },
            {
              "ModuleName": "decision_function",
              "InstanceName": "grp_decision_function_fu_564"
            },
            {
              "ModuleName": "decision_function",
              "InstanceName": "grp_decision_function_fu_650"
            },
            {
              "ModuleName": "decision_function",
              "InstanceName": "grp_decision_function_fu_736"
            },
            {
              "ModuleName": "decision_function",
              "InstanceName": "grp_decision_function_fu_822"
            },
            {
              "ModuleName": "decision_function",
              "InstanceName": "grp_decision_function_fu_908"
            },
            {
              "ModuleName": "decision_function",
              "InstanceName": "grp_decision_function_fu_994"
            },
            {
              "ModuleName": "decision_function",
              "InstanceName": "grp_decision_function_fu_1080"
            },
            {
              "ModuleName": "decision_function",
              "InstanceName": "grp_decision_function_fu_1166"
            },
            {
              "ModuleName": "decision_function",
              "InstanceName": "grp_decision_function_fu_1252"
            },
            {
              "ModuleName": "decision_function",
              "InstanceName": "grp_decision_function_fu_1338"
            },
            {
              "ModuleName": "decision_function",
              "InstanceName": "grp_decision_function_fu_1424"
            },
            {
              "ModuleName": "decision_function",
              "InstanceName": "grp_decision_function_fu_1510"
            },
            {
              "ModuleName": "decision_function",
              "InstanceName": "grp_decision_function_fu_1596"
            },
            {
              "ModuleName": "decision_function",
              "InstanceName": "grp_decision_function_fu_1675"
            },
            {
              "ModuleName": "decision_function",
              "InstanceName": "grp_decision_function_fu_1754"
            },
            {
              "ModuleName": "decision_function",
              "InstanceName": "grp_decision_function_fu_1833"
            },
            {
              "ModuleName": "decision_function",
              "InstanceName": "grp_decision_function_fu_1912"
            },
            {
              "ModuleName": "decision_function",
              "InstanceName": "grp_decision_function_fu_1991"
            },
            {
              "ModuleName": "decision_function",
              "InstanceName": "grp_decision_function_fu_2070"
            },
            {
              "ModuleName": "decision_function",
              "InstanceName": "grp_decision_function_fu_2149"
            },
            {
              "ModuleName": "decision_function",
              "InstanceName": "grp_decision_function_fu_2228"
            },
            {
              "ModuleName": "decision_function",
              "InstanceName": "grp_decision_function_fu_2307"
            },
            {
              "ModuleName": "decision_function",
              "InstanceName": "grp_decision_function_fu_2386"
            },
            {
              "ModuleName": "decision_function",
              "InstanceName": "grp_decision_function_fu_2465"
            },
            {
              "ModuleName": "decision_function",
              "InstanceName": "grp_decision_function_fu_2544"
            },
            {
              "ModuleName": "decision_function",
              "InstanceName": "grp_decision_function_fu_2623"
            },
            {
              "ModuleName": "decision_function",
              "InstanceName": "grp_decision_function_fu_2702"
            },
            {
              "ModuleName": "decision_function",
              "InstanceName": "grp_decision_function_fu_2781"
            },
            {
              "ModuleName": "decision_function",
              "InstanceName": "grp_decision_function_fu_2860"
            },
            {
              "ModuleName": "decision_function",
              "InstanceName": "grp_decision_function_fu_2939"
            },
            {
              "ModuleName": "decision_function",
              "InstanceName": "grp_decision_function_fu_3018"
            },
            {
              "ModuleName": "decision_function",
              "InstanceName": "grp_decision_function_fu_3097"
            },
            {
              "ModuleName": "decision_function",
              "InstanceName": "grp_decision_function_fu_3176"
            },
            {
              "ModuleName": "decision_function",
              "InstanceName": "grp_decision_function_fu_3255"
            },
            {
              "ModuleName": "decision_function",
              "InstanceName": "grp_decision_function_fu_3334"
            },
            {
              "ModuleName": "decision_function",
              "InstanceName": "grp_decision_function_fu_3413"
            },
            {
              "ModuleName": "decision_function",
              "InstanceName": "grp_decision_function_fu_3492"
            },
            {
              "ModuleName": "decision_function",
              "InstanceName": "grp_decision_function_fu_3571"
            },
            {
              "ModuleName": "decision_function",
              "InstanceName": "grp_decision_function_fu_3650"
            },
            {
              "ModuleName": "decision_function",
              "InstanceName": "grp_decision_function_fu_3729"
            },
            {
              "ModuleName": "decision_function",
              "InstanceName": "grp_decision_function_fu_3808"
            },
            {
              "ModuleName": "decision_function",
              "InstanceName": "grp_decision_function_fu_3887"
            },
            {
              "ModuleName": "decision_function",
              "InstanceName": "grp_decision_function_fu_3966"
            },
            {
              "ModuleName": "decision_function",
              "InstanceName": "grp_decision_function_fu_4045"
            },
            {
              "ModuleName": "decision_function",
              "InstanceName": "grp_decision_function_fu_4124"
            },
            {
              "ModuleName": "decision_function",
              "InstanceName": "grp_decision_function_fu_4203"
            },
            {
              "ModuleName": "decision_function",
              "InstanceName": "grp_decision_function_fu_4282"
            },
            {
              "ModuleName": "decision_function",
              "InstanceName": "grp_decision_function_fu_4361"
            },
            {
              "ModuleName": "decision_function",
              "InstanceName": "grp_decision_function_fu_4440"
            },
            {
              "ModuleName": "decision_function",
              "InstanceName": "grp_decision_function_fu_4519"
            },
            {
              "ModuleName": "decision_function",
              "InstanceName": "grp_decision_function_fu_4598"
            },
            {
              "ModuleName": "decision_function",
              "InstanceName": "grp_decision_function_fu_4677"
            },
            {
              "ModuleName": "decision_function",
              "InstanceName": "grp_decision_function_fu_4756"
            },
            {
              "ModuleName": "decision_function",
              "InstanceName": "grp_decision_function_fu_4835"
            },
            {
              "ModuleName": "decision_function",
              "InstanceName": "grp_decision_function_fu_4914"
            },
            {
              "ModuleName": "decision_function",
              "InstanceName": "grp_decision_function_fu_4993"
            },
            {
              "ModuleName": "decision_function",
              "InstanceName": "grp_decision_function_fu_5072"
            },
            {
              "ModuleName": "decision_function",
              "InstanceName": "grp_decision_function_fu_5151"
            },
            {
              "ModuleName": "decision_function",
              "InstanceName": "grp_decision_function_fu_5230"
            },
            {
              "ModuleName": "decision_function",
              "InstanceName": "grp_decision_function_fu_5309"
            },
            {
              "ModuleName": "decision_function",
              "InstanceName": "grp_decision_function_fu_5388"
            },
            {
              "ModuleName": "decision_function",
              "InstanceName": "grp_decision_function_fu_5467"
            },
            {
              "ModuleName": "decision_function",
              "InstanceName": "grp_decision_function_fu_5546"
            },
            {
              "ModuleName": "decision_function",
              "InstanceName": "grp_decision_function_fu_5625"
            },
            {
              "ModuleName": "decision_function",
              "InstanceName": "grp_decision_function_fu_5704"
            },
            {
              "ModuleName": "decision_function",
              "InstanceName": "grp_decision_function_fu_5783"
            },
            {
              "ModuleName": "decision_function",
              "InstanceName": "grp_decision_function_fu_5862"
            },
            {
              "ModuleName": "decision_function",
              "InstanceName": "grp_decision_function_fu_5941"
            },
            {
              "ModuleName": "decision_function",
              "InstanceName": "grp_decision_function_fu_6020"
            },
            {
              "ModuleName": "decision_function",
              "InstanceName": "grp_decision_function_fu_6099"
            },
            {
              "ModuleName": "decision_function",
              "InstanceName": "grp_decision_function_fu_6178"
            },
            {
              "ModuleName": "decision_function",
              "InstanceName": "grp_decision_function_fu_6257"
            },
            {
              "ModuleName": "decision_function",
              "InstanceName": "grp_decision_function_fu_6336"
            },
            {
              "ModuleName": "decision_function",
              "InstanceName": "grp_decision_function_fu_6415"
            },
            {
              "ModuleName": "decision_function",
              "InstanceName": "grp_decision_function_fu_6494"
            },
            {
              "ModuleName": "decision_function",
              "InstanceName": "grp_decision_function_fu_6573"
            },
            {
              "ModuleName": "decision_function",
              "InstanceName": "grp_decision_function_fu_6652"
            },
            {
              "ModuleName": "decision_function",
              "InstanceName": "grp_decision_function_fu_6731"
            },
            {
              "ModuleName": "decision_function",
              "InstanceName": "grp_decision_function_fu_6810"
            },
            {
              "ModuleName": "decision_function",
              "InstanceName": "grp_decision_function_fu_6889"
            },
            {
              "ModuleName": "decision_function",
              "InstanceName": "grp_decision_function_fu_6968"
            },
            {
              "ModuleName": "decision_function",
              "InstanceName": "grp_decision_function_fu_7047"
            },
            {
              "ModuleName": "decision_function",
              "InstanceName": "grp_decision_function_fu_7126"
            },
            {
              "ModuleName": "decision_function",
              "InstanceName": "grp_decision_function_fu_7205"
            },
            {
              "ModuleName": "decision_function",
              "InstanceName": "grp_decision_function_fu_7284"
            },
            {
              "ModuleName": "decision_function",
              "InstanceName": "grp_decision_function_fu_7363"
            },
            {
              "ModuleName": "decision_function",
              "InstanceName": "grp_decision_function_fu_7442"
            },
            {
              "ModuleName": "decision_function",
              "InstanceName": "grp_decision_function_fu_7521"
            },
            {
              "ModuleName": "decision_function",
              "InstanceName": "grp_decision_function_fu_7600"
            },
            {
              "ModuleName": "decision_function",
              "InstanceName": "grp_decision_function_fu_7679"
            },
            {
              "ModuleName": "decision_function",
              "InstanceName": "grp_decision_function_fu_7758"
            },
            {
              "ModuleName": "decision_function",
              "InstanceName": "grp_decision_function_fu_7837"
            },
            {
              "ModuleName": "decision_function",
              "InstanceName": "grp_decision_function_fu_7916"
            },
            {
              "ModuleName": "decision_function",
              "InstanceName": "grp_decision_function_fu_7995"
            },
            {
              "ModuleName": "decision_function",
              "InstanceName": "grp_decision_function_fu_8074"
            },
            {
              "ModuleName": "decision_function",
              "InstanceName": "grp_decision_function_fu_8153"
            },
            {
              "ModuleName": "decision_function",
              "InstanceName": "grp_decision_function_fu_8232"
            },
            {
              "ModuleName": "decision_function",
              "InstanceName": "grp_decision_function_fu_8311"
            },
            {
              "ModuleName": "decision_function",
              "InstanceName": "grp_decision_function_fu_8390"
            }
          ]
        }]
    },
    "Info": {
      "decision_function": {
        "FunctionProtocol": "ap_ctrl_hs",
        "isTaskLevelControl": "1",
        "isPipelined": "1",
        "isCombinational": "0",
        "isOneStateSeq": "0"
      },
      "decision_function_1": {
        "FunctionProtocol": "ap_ctrl_hs",
        "isTaskLevelControl": "1",
        "isPipelined": "1",
        "isCombinational": "0",
        "isOneStateSeq": "0"
      },
      "my_prj": {
        "FunctionProtocol": "ap_ctrl_hs",
        "isTaskLevelControl": "1",
        "isPipelined": "1",
        "isCombinational": "0",
        "isOneStateSeq": "0"
      }
    },
    "Metrics": {
      "decision_function": {
        "Latency": {
          "LatencyBest": "2",
          "LatencyAvg": "2",
          "LatencyWorst": "2",
          "PipelineII": "1",
          "PipelineDepth": "3",
          "PipelineType": "function"
        },
        "Timing": {
          "Target": "4.17",
          "Uncertainty": "0.52",
          "Estimate": "3.601"
        },
        "Area": {
          "FF": "412",
          "LUT": "1386",
          "BRAM_18K": "0",
          "DSP48E": "0",
          "URAM": "0"
        }
      },
      "decision_function_1": {
        "Latency": {
          "LatencyBest": "5",
          "LatencyAvg": "5",
          "LatencyWorst": "5",
          "PipelineII": "1",
          "PipelineDepth": "6",
          "PipelineType": "function"
        },
        "Timing": {
          "Target": "4.17",
          "Uncertainty": "0.52",
          "Estimate": "3.601"
        },
        "Area": {
          "FF": "43929",
          "LUT": "141561",
          "BRAM_18K": "0",
          "DSP48E": "0",
          "URAM": "0"
        }
      },
      "my_prj": {
        "Latency": {
          "LatencyBest": "6",
          "LatencyAvg": "6",
          "LatencyWorst": "6",
          "PipelineII": "1",
          "PipelineDepth": "7",
          "PipelineType": "function"
        },
        "Timing": {
          "Target": "4.17",
          "Uncertainty": "0.52",
          "Estimate": "3.601"
        },
        "Area": {
          "FF": "43936",
          "LUT": "141565",
          "BRAM_18K": "0",
          "DSP48E": "0",
          "URAM": "0"
        }
      }
    }
  },
  "Sdx": {
    "Target": "none",
    "ProfileOption": "0",
    "ProfileType": "none",
    "XO": "",
    "KernelName": "my_prj",
    "EnableXoSwEmu": "1"
  },
  "GenData": {
    "DataVersion": "0.2",
    "Time": "2020-09-23 16:51:20 MDT",
    "ToolName": "vivado_hls",
    "ToolVersion": "2019.1"
  }
}
